JSON_file_streaming_GCS_BigQuery/__init__.py
JSON_file_streaming_GCS_BigQuery/main.py
JSON_file_streaming_GCS_BigQuery-0.0.dist-info/METADATA
JSON_file_streaming_GCS_BigQuery-0.0.dist-info/WHEEL
JSON_file_streaming_GCS_BigQuery-0.0.dist-info/entry_points.txt
JSON_file_streaming_GCS_BigQuery-0.0.dist-info/top_level.txt
JSON_file_streaming_GCS_BigQuery-0.0.dist-info/RECORD
