Metadata-Version: 2.1
Name: JSON-file-streaming-GCS-BigQuery
Version: 0.0
